graiax/silkcoder/ffmpeg.py
graiax/silkcoder/__main__.py
graiax/silkcoder/__init__.pyi
graiax/silkcoder/silkv3.py
graiax/silkcoder/utils.py
graiax/silkcoder/libsndfile.py
graiax/silkcoder/__init__.py
graiax/silkcoder/_silkv3.cpython-39-aarch64-linux-gnu.so
graiax/silkcoder/_silkv3.pyi
graiax/silkcoder/wav.py
graiax_silkcoder-0.3.6.dist-info/WHEEL
graiax_silkcoder-0.3.6.dist-info/RECORD
graiax_silkcoder-0.3.6.dist-info/METADATA
graiax_silkcoder-0.3.6.dist-info/licenses/LICENSE
