Metadata-Version: 2.1
Name: graiax-silkcoder
Version: 0.3.6
Summary: transform audio file to silk
License: BSD-3-Clause
Keywords: silkv3
Author-email: I Love Study <1450069615@qq.com>
Requires-Python: >=3.8
Provides-Extra: ffmpeg
Provides-Extra: libsndfile
Project-URL: repository, https://github.com/I-love-study/graiax-silkcoder
